oarepo_tools/__init__.py
oarepo_tools/make_translations.py
oarepo_tools/babel/__init__.py
oarepo_tools/babel/babel.ini
oarepo_tools/i18next/__init__.py
oarepo_tools/i18next/i18next-scanner.config.js
oarepo_tools/i18next/i18next.js
oarepo_tools/i18next/package-lock.json
oarepo_tools/i18next/package.json
oarepo_tools/i18next/scripts/compileCatalog.js
oarepo_tools/i18next/scripts/generatePOT.sh
oarepo_tools-0.2.6.dist-info/METADATA
oarepo_tools-0.2.6.dist-info/WHEEL
oarepo_tools-0.2.6.dist-info/entry_points.txt
oarepo_tools-0.2.6.dist-info/top_level.txt
oarepo_tools-0.2.6.dist-info/RECORD
