Metadata-Version: 2.1
Name: oarepo-tools
Version: 0.2.6
Summary: OARepo tools
Author-email: Miroslav Simek <miroslav.simek@cesnet.cz>
Requires-Dist: click
Requires-Dist: polib
Requires-Dist: jinja2
Requires-Dist: babel
Requires-Dist: PyYAML
Requires-Dist: jinjax
Provides-Extra: dev
Requires-Dist: pytest>=7.1.2; extra == "dev"
Requires-Dist: oarepo-runtime>=1.4.44; extra == "dev"
Requires-Dist: black; extra == "dev"
Requires-Dist: autoflake; extra == "dev"
Requires-Dist: isort; extra == "dev"
Requires-Dist: pytest-docker; extra == "dev"
Requires-Dist: pytest-invenio; extra == "dev"
Requires-Dist: jinjax==0.37; extra == "dev"
Provides-Extra: tests
Requires-Dist: pytest>=7.1.2; extra == "tests"
Requires-Dist: oarepo-runtime>=1.4.44; extra == "tests"
Requires-Dist: pytest-mock; extra == "tests"
Requires-Dist: pytest-invenio; extra == "tests"
Requires-Dist: jinjax==0.37; extra == "tests"
